LICENSE
MANIFEST.in
setup.py
heol_humanoid/__init__.py
heol_humanoid/_version.py
heol_humanoid/heol_humanoid.py
heol_humanoid.egg-info/PKG-INFO
heol_humanoid.egg-info/SOURCES.txt
heol_humanoid.egg-info/dependency_links.txt
heol_humanoid.egg-info/not-zip-safe
heol_humanoid.egg-info/requires.txt
heol_humanoid.egg-info/top_level.txt
heol_humanoid/configuration/heol_humanoid.json
heol_humanoid/doc/heol quickstart.ipynb
heol_humanoid/doc/idmotor.pdf
heol_humanoid/doc/monmove.move
heol_humanoid/primitives/__init__.py
heol_humanoid/primitives/postures.py
heol_humanoid/vrep-scene/heol_humanoid.ttt