Metadata-Version: 1.0
Name: heol-humanoid
Version: 0.2.1
Summary:  Heol Software Library
Home-page: https://github.com/Heolrobotics/Heol-humanoid
Author: Alexandre Le Fahler, Julien Jehl
Author-email: ???
License: GNU GENERAL PUBLIC LICENSE Version 3
Platform: UNKNOWN
